{
  "project_info": {
    "project_number": "620120334203",
    "project_id": "sertifikasi-jmp-4-agt",
    "storage_bucket": "sertifikasi-jmp-4-agt.appspot.com"
  },
  "client": [
    {
      "client_info": {
        "mobilesdk_app_id": "1:620120334203:android:f82cd7b6447c4d8a89a7de",
        "android_client_info": {
          "package_name": "com.project.user"
        }
      },
      "oauth_client": [],
      "api_key": [
        {
          "current_key": "AIzaSyD4_RHy8t1x7G5hA2lI9ZgXgKDyETuZIfI"
        }
      ],
      "services": {
        "appinvite_service": {
          "other_platform_oauth_client": []
        }
      }
    }
  ],
  "configuration_version": "1"
}